{
  "year": {
    "2020": [
      1.1100,
      1.0905,
      1.1063,
      1.0862,
      1.0902,
      1.1255,
      1.1463,
      1.1828,
      1.1792,
      1.1775,
      1.1838,
      1.2170
    ],
    "2021": [
      1.2171,
      1.2098,
      1.1899,
      1.1989,
      1.2146,
      1.2047,
      1.1822,
      1.1772,
      1.1770,
      1.1601,
      1.1414,
      1.1304
    ],
    "2022": [
      1.1314,
      1.1342,
      1.1019,
      1.0819,
      1.0579,
      1.0566,
      1.0179,
      1.0128,
      0.9904,
      0.9826,
      1.0201,
      1.0589
    ],
    "2023": [
      1.0769,
      1.0715,
      1.0706,
      1.0968,
      1.0868,
      1.0840,
      1.1058,
      1.0909,
      1.0684,
      1.0563,
      1.0808,
      1.0903
    ]
  }
}

